dv_data_generator/__init__.py
dv_data_generator/dv_data_director.py
dv_data_generator/settings.py
dv_data_generator/builders/__init__.py
dv_data_generator/builders/dv_report_builder.py
dv_data_generator/builders/dv_request_builder.py
dv_data_generator/helpers/__init__.py
dv_data_generator/helpers/assertion.py
dv_data_generator/helpers/dbm.py
dv_data_generator/helpers/file.py
dv_data_generator/helpers/google_api.py
dv_data_generator/services/__init__.py
dv_data_generator/services/display_video.py
dv_data_generator/services/double_click_bid_manager.py
tests/__init__.py
tests/debug_dbm_service.py
tests/test_utils.py
dv_data_generator-0.4.2.dist-info/METADATA
dv_data_generator-0.4.2.dist-info/WHEEL
dv_data_generator-0.4.2.dist-info/top_level.txt
dv_data_generator-0.4.2.dist-info/RECORD
