Metadata-Version: 2.1
Name: dv-data-generator
Version: 0.4.2
Summary: UNKNOWN
Home-page: https://gitlab.com/dqna/dv-data-generator
License: UNKNOWN
Platform: UNKNOWN
Requires-Python: >=3.8
Requires-Dist: requests
Requires-Dist: httplib2
Requires-Dist: google-api-core
Requires-Dist: google-api-python-client
Requires-Dist: google-auth
Requires-Dist: google-cloud-core
Requires-Dist: google-resumable-media
Requires-Dist: googleapis-common-protos
Requires-Dist: google-auth-oauthlib
Requires-Dist: oauth2client
